flask_prometheus_metrics/__init__.py
flask_prometheus_metrics/example.py
flask_prometheus_metrics/metrics.py
flask_prometheus_metrics-1.0.0.dist-info/LICENSE
flask_prometheus_metrics-1.0.0.dist-info/METADATA
flask_prometheus_metrics-1.0.0.dist-info/WHEEL
flask_prometheus_metrics-1.0.0.dist-info/top_level.txt
flask_prometheus_metrics-1.0.0.dist-info/RECORD
